rqwest/__init__.py
rqwest/example.py
rqwest-0.1.0.dist-info/LICENSE
rqwest-0.1.0.dist-info/METADATA
rqwest-0.1.0.dist-info/WHEEL
rqwest-0.1.0.dist-info/RECORD
