Metadata-Version: 2.1
Name: rqwest
Version: 0.1.0
Summary: An intuitive and robust Python HTTP/WebSocket Client featuring TLS/JA3/JA4/HTTP2 fingerprint impersonate
Home-page: https://github.com/0x676e67/rqwest
License: MIT
Author: 0x676e67
Author-email: gngppz@gmail.com
Requires-Python: >=3.8,<4.0
Classifier: License :: OSI Approved :: MIT License
Classifier: Programming Language :: Python :: 3
Classifier: Programming Language :: Python :: 3.8
Classifier: Programming Language :: Python :: 3.9
Classifier: Programming Language :: Python :: 3.10
Classifier: Programming Language :: Python :: 3.11
Classifier: Programming Language :: Python :: 3.12
Project-URL: Repository, https://github.com/0x676e67/rqwest
